README.md
setup.cfg
setup.py
pythonbits/__init__.py
pythonbits/__main__.py
pythonbits/bb.py
pythonbits/config.py
pythonbits/ffmpeg.py
pythonbits/imagehosting.py
pythonbits/imdb.py
pythonbits/imgur.py
pythonbits/logging.py
pythonbits/ptpimg.py
pythonbits/scene.py
pythonbits/submission.py
pythonbits/templating.py
pythonbits/torrent.py
pythonbits/tracker.py
pythonbits/tvdb.py
pythonbits.egg-info/PKG-INFO
pythonbits.egg-info/SOURCES.txt
pythonbits.egg-info/dependency_links.txt
pythonbits.egg-info/entry_points.txt
pythonbits.egg-info/requires.txt
pythonbits.egg-info/top_level.txt