Metadata-Version: 1.2
Name: pythonbits
Version: 3.0.3
Summary: A pretty printer for media
Home-page: https://github.com/mueslo/pythonBits
License: GPLv3
Platform: UNKNOWN
Classifier: Operating System :: OS Independent
Classifier: Programming Language :: Python
Classifier: Programming Language :: Python :: 3
Classifier: Programming Language :: Python :: 3.5
Classifier: Programming Language :: Python :: 3.6
Classifier: Programming Language :: Python :: 3.7
Classifier: Programming Language :: Python :: 3.8
Classifier: License :: OSI Approved :: GNU General Public License v3 (GPLv3)
Classifier: Topic :: Internet
Classifier: Topic :: Multimedia
Classifier: Topic :: Utilities
Requires-Python: >=3.5,<4.0
